Bin_BCD_Input.v
module Bin_BCD_Input();
	parameter PERIOD = 10;

	reg[7:0] currIn;
	reg clk, reset;

	wire[7:0] currIn_w;
	wire[11:0] decOut;                                                                                                                                                                                                                                                                                                                                                                                                                                                                                                                                                         

	integer i;



	assign currIn_w = currIn;

	initial begin
		$dumpfile("Bin_BCD.vcd");
    	$dumpvars(0, Bin_BCD_Input);
	end
	
	always #PERIOD clk=~clk;
	
	BinToBCD dut(.decOut(decOut), .binIn(currIn_w), .clk(clk), .reset(reset));

	initial begin
		clk = 0;
		currIn = 8'b1100100;
		reset = 1; #40;
		reset = 0; #150;
		for (i=0; i < 255-100+1; i++) begin
			currIn = currIn + 1; #180;
		end
		$finish;
	end

endmodule



module BinToBCD(decOut, binIn, clk, reset);
	parameter BINSIZE = 8;

	output [11:0] decOut;
	input [BINSIZE-1:0] binIn;
	input clk, reset;

	reg [12+BINSIZE-1:0] dec_and_bin;
	reg [3:0] counter;
	reg [12+BINSIZE-1:0] bcdOut;

	assign decOut = bcdOut[19:8];

	always @(posedge clk) begin
		if (reset) begin 
			dec_and_bin <= {12'b0, binIn}; // initialized at 000... | input
			counter <= 4'b1;
			bcdOut = 12'b0;	
		end else begin
			dec_and_bin = dec_and_bin << 1;
			
			if (counter == 4'b1001) begin
				counter = 4'b0;
				dec_and_bin = {12'b0, binIn};	
			end else begin

			// double dabble logic
				if (dec_and_bin[11:8] > 4'b0100 && counter < 4'b1000) 
				 		dec_and_bin[11:8] = dec_and_bin[11:8] + 4'b0011;

				if (dec_and_bin[15:12] > 4'b0100 && counter < 4'b1000) 
				 		dec_and_bin[15:12] = dec_and_bin[15:12] + 4'b0011;

				if (dec_and_bin[19:16] > 4'b0100 && counter < 4'b1000) 
				 		dec_and_bin[19:16] = dec_and_bin[19:16] + 4'b0011;
			end

			if (counter == 4'b1000) //set bcdOut in the cycle before the last
			 	bcdOut = dec_and_bin;

			counter = counter + 1'b1;
		end
	end
endmodule

Bin_BCD.vcd
$date
	Sun Sep 22 23:22:57 2019
$end
$version
	Icarus Verilog
$end
$timescale
	1s
$end
$scope module Bin_BCD_Input $end
$var wire 8 ! currIn_w [7:0] $end
$var wire 12 " decOut [11:0] $end
$var reg 1 # clk $end
$var reg 8 $ currIn [7:0] $end
$var reg 1 % reset $end
$var integer 32 & i [31:0] $end
$scope module dut $end
$var wire 8 ' binIn [7:0] $end
$var wire 1 # clk $end
$var wire 1 % reset $end
$var wire 12 ( decOut [11:0] $end
$var reg 20 ) bcdOut [19:0] $end
$var reg 4 * counter [3:0] $end
$var reg 20 + dec_and_bin [19:0] $end
$upscope $end
$upscope $end
$enddefinitions $end
#0
$dumpvars
bx +
bx *
bx )
bx (
b1100100 '
bx &
1%
b1100100 $
0#
bx "
b1100100 !
$end
#10
b1 *
b1100100 +
b0 "
b0 (
b0 )
1#
#20
0#
#30
1#
#40
0#
0%
#50
b10 *
b11001000 +
1#
#60
0#
#70
b11 *
b110010000 +
1#
#80
0#
#90
b100 *
b1100100000 +
1#
#100
0#
#110
b101 *
b100101000000 +
1#
#120
0#
#130
b110 *
b1001010000000 +
1#
#140
0#
#150
b111 *
b10100000000000 +
1#
#160
0#
#170
b1000 *
b1000000000000000 +
1#
#180
0#
#190
b100000000 "
b100000000 (
b1001 *
b10000000000000000 )
b10000000000000000 +
1#
b1100101 !
b1100101 '
b1100101 $
b0 &
#200
0#
#210
b1 *
b1100101 +
1#
#220
0#
#230
b10 *
b11001010 +
1#
#240
0#
#250
b11 *
b110010100 +
1#
#260
0#
#270
b100 *
b1100101000 +
1#
#280
0#
#290
b101 *
b100101010000 +
1#
#300
0#
#310
b110 *
b1001010100000 +
1#
#320
0#
#330
b111 *
b10100001000000 +
1#
#340
0#
#350
b1000 *
b1000000010000000 +
1#
#360
0#
#370
b100000001 "
b100000001 (
b1001 *
b10000000100000000 )
b10000000100000000 +
1#
b1100110 !
b1100110 '
b1100110 $
b1 &
#380
0#
#390
b1 *
b1100110 +
1#
#400
0#
#410
b10 *
b11001100 +
1#
#420
0#
#430
b11 *
b110011000 +
1#
#440
0#
#450
b100 *
b1100110000 +
1#
#460
0#
#470
b101 *
b100101100000 +
1#
#480
0#
#490
b110 *
b1001011000000 +
1#
#500
0#
#510
b111 *
b10100010000000 +
1#
#520
0#
#530
b1000 *
b1000000100000000 +
1#
#540
0#
#550
b100000010 "
b100000010 (
b1001 *
b10000001000000000 )
b10000001000000000 +
1#
b1100111 !
b1100111 '
b1100111 $
b10 &
#560
0#
#570
b1 *
b1100111 +
1#
#580
0#
#590
b10 *
b11001110 +
1#
#600
0#
#610
b11 *
b110011100 +
1#
#620
0#
#630
b100 *
b1100111000 +
1#
#640
0#
#650
b101 *
b100101110000 +
1#
#660
0#
#670
b110 *
b1001011100000 +
1#
#680
0#
#690
b111 *
b10100011000000 +
1#
#700
0#
#710
b1000 *
b1000000110000000 +
1#
#720
0#
#730
b100000011 "
b100000011 (
b1001 *
b10000001100000000 )
b10000001100000000 +
1#
b1101000 !
b1101000 '
b1101000 $
b11 &
#740
0#
#750
b1 *
b1101000 +
1#
#760
0#
#770
b10 *
b11010000 +
1#
#780
0#
#790
b11 *
b110100000 +
1#
#800
0#
#810
b100 *
b1101000000 +
1#
#820
0#
#830
b101 *
b100110000000 +
1#
#840
0#
#850
b110 *
b1001100000000 +
1#
#860
0#
#870
b111 *
b10100100000000 +
1#
#880
0#
#890
b1000 *
b1000001000000000 +
1#
#900
0#
#910
b100000100 "
b100000100 (
b1001 *
b10000010000000000 )
b10000010000000000 +
1#
b1101001 !
b1101001 '
b1101001 $
b100 &
#920
0#
#930
b1 *
b1101001 +
1#
#940
0#
#950
b10 *
b11010010 +
1#
#960
0#
#970
b11 *
b110100100 +
1#
#980
0#
#990
b100 *
b1101001000 +
1#
#1000
0#
#1010
b101 *
b100110010000 +
1#
#1020
0#
#1030
b110 *
b1001100100000 +
1#
#1040
0#
#1050
b111 *
b10100101000000 +
1#
#1060
0#
#1070
b1000 *
b1000001010000000 +
1#
#1080
0#
#1090
b100000101 "
b100000101 (
b1001 *
b10000010100000000 )
b10000010100000000 +
1#
b1101010 !
b1101010 '
b1101010 $
b101 &
#1100
0#
#1110
b1 *
b1101010 +
1#
#1120
0#
#1130
b10 *
b11010100 +
1#
#1140
0#
#1150
b11 *
b110101000 +
1#
#1160
0#
#1170
b100 *
b1101010000 +
1#
#1180
0#
#1190
b101 *
b100110100000 +
1#
#1200
0#
#1210
b110 *
b1001101000000 +
1#
#1220
0#
#1230
b111 *
b10100110000000 +
1#
#1240
0#
#1250
b1000 *
b1000001100000000 +
1#
#1260
0#
#1270
b100000110 "
b100000110 (
b1001 *
b10000011000000000 )
b10000011000000000 +
1#
b1101011 !
b1101011 '
b1101011 $
b110 &
#1280
0#
#1290
b1 *
b1101011 +
1#
#1300
0#
#1310
b10 *
b11010110 +
1#
#1320
0#
#1330
b11 *
b110101100 +
1#
#1340
0#
#1350
b100 *
b1101011000 +
1#
#1360
0#
#1370
b101 *
b100110110000 +
1#
#1380
0#
#1390
b110 *
b1001101100000 +
1#
#1400
0#
#1410
b111 *
b10100111000000 +
1#
#1420
0#
#1430
b1000 *
b1000001110000000 +
1#
#1440
0#
#1450
b100000111 "
b100000111 (
b1001 *
b10000011100000000 )
b10000011100000000 +
1#
b1101100 !
b1101100 '
b1101100 $
b111 &
#1460
0#
#1470
b1 *
b1101100 +
1#
#1480
0#
#1490
b10 *
b11011000 +
1#
#1500
0#
#1510
b11 *
b110110000 +
1#
#1520
0#
#1530
b100 *
b1101100000 +
1#
#1540
0#
#1550
b101 *
b100111000000 +
1#
#1560
0#
#1570
b110 *
b1001110000000 +
1#
#1580
0#
#1590
b111 *
b10101000000000 +
1#
#1600
0#
#1610
b1000 *
b1000010000000000 +
1#
#1620
0#
#1630
b100001000 "
b100001000 (
b1001 *
b10000100000000000 )
b10000100000000000 +
1#
b1101101 !
b1101101 '
b1101101 $
b1000 &
#1640
0#
#1650
b1 *
b1101101 +
1#
#1660
0#
#1670
b10 *
b11011010 +
1#
#1680
0#
#1690
b11 *
b110110100 +
1#
#1700
0#
#1710
b100 *
b1101101000 +
1#
#1720
0#
#1730
b101 *
b100111010000 +
1#
#1740
0#
#1750
b110 *
b1001110100000 +
1#
#1760
0#
#1770
b111 *
b10101001000000 +
1#
#1780
0#
#1790
b1000 *
b1000010010000000 +
1#
#1800
0#
#1810
b100001001 "
b100001001 (
b1001 *
b10000100100000000 )
b10000100100000000 +
1#
b1101110 !
b1101110 '
b1101110 $
b1001 &
#1820
0#
#1830
b1 *
b1101110 +
1#
#1840
0#
#1850
b10 *
b11011100 +
1#
#1860
0#
#1870
b11 *
b110111000 +
1#
#1880
0#
#1890
b100 *
b1101110000 +
1#
#1900
0#
#1910
b101 *
b100111100000 +
1#
#1920
0#
#1930
b110 *
b1001111000000 +
1#
#1940
0#
#1950
b111 *
b10101010000000 +
1#
#1960
0#
#1970
b1000 *
b1000100000000000 +
1#
#1980
0#
#1990
b100010000 "
b100010000 (
b1001 *
b10001000000000000 )
b10001000000000000 +
1#
b1101111 !
b1101111 '
b1101111 $
b1010 &
#2000
0#
#2010
b1 *
b1101111 +
1#
#2020
0#
#2030
b10 *
b11011110 +
1#
#2040
0#
#2050
b11 *
b110111100 +
1#
#2060
0#
#2070
b100 *
b1101111000 +
1#
#2080
0#
#2090
b101 *
b100111110000 +
1#
#2100
0#
#2110
b110 *
b1001111100000 +
1#
#2120
0#
#2130
b111 *
b10101011000000 +
1#
#2140
0#
#2150
b1000 *
b1000100010000000 +
1#
#2160
0#
#2170
b100010001 "
b100010001 (
b1001 *
b10001000100000000 )
b10001000100000000 +
1#
b1110000 !
b1110000 '
b1110000 $
b1011 &
#2180
0#
#2190
b1 *
b1110000 +
1#
#2200
0#
#2210
b10 *
b11100000 +
1#
#2220
0#
#2230
b11 *
b111000000 +
1#
#2240
0#
#2250
b100 *
b1110000000 +
1#
#2260
0#
#2270
b101 *
b101000000000 +
1#
#2280
0#
#2290
b110 *
b1010000000000 +
1#
#2300
0#
#2310
b111 *
b10101100000000 +
1#
#2320
0#
#2330
b1000 *
b1000100100000000 +
1#
#2340
0#
#2350
b100010010 "
b100010010 (
b1001 *
b10001001000000000 )
b10001001000000000 +
1#
b1110001 !
b1110001 '
b1110001 $
b1100 &
#2360
0#
#2370
b1 *
b1110001 +
1#
#2380
0#
#2390
b10 *
b11100010 +
1#
#2400
0#
#2410
b11 *
b111000100 +
1#
#2420
0#
#2430
b100 *
b1110001000 +
1#
#2440
0#
#2450
b101 *
b101000010000 +
1#
#2460
0#
#2470
b110 *
b1010000100000 +
1#
#2480
0#
#2490
b111 *
b10101101000000 +
1#
#2500
0#
#2510
b1000 *
b1000100110000000 +
1#
#2520
0#
#2530
b100010011 "
b100010011 (
b1001 *
b10001001100000000 )
b10001001100000000 +
1#
b1110010 !
b1110010 '
b1110010 $
b1101 &
#2540
0#
#2550
b1 *
b1110010 +
1#
#2560
0#
#2570
b10 *
b11100100 +
1#
#2580
0#
#2590
b11 *
b111001000 +
1#
#2600
0#
#2610
b100 *
b1110010000 +
1#
#2620
0#
#2630
b101 *
b101000100000 +
1#
#2640
0#
#2650
b110 *
b1010001000000 +
1#
#2660
0#
#2670
b111 *
b10101110000000 +
1#
#2680
0#
#2690
b1000 *
b1000101000000000 +
1#
#2700
0#
#2710
b100010100 "
b100010100 (
b1001 *
b10001010000000000 )
b10001010000000000 +
1#
b1110011 !
b1110011 '
b1110011 $
b1110 &
#2720
0#
#2730
b1 *
b1110011 +
1#
#2740
0#
#2750
b10 *
b11100110 +
1#
#2760
0#
#2770
b11 *
b111001100 +
1#
#2780
0#
#2790
b100 *
b1110011000 +
1#
#2800
0#
#2810
b101 *
b101000110000 +
1#
#2820
0#
#2830
b110 *
b1010001100000 +
1#
#2840
0#
#2850
b111 *
b10101111000000 +
1#
#2860
0#
#2870
b1000 *
b1000101010000000 +
1#
#2880
0#
#2890
b100010101 "
b100010101 (
b1001 *
b10001010100000000 )
b10001010100000000 +
1#
b1110100 !
b1110100 '
b1110100 $
b1111 &
#2900
0#
#2910
b1 *
b1110100 +
1#
#2920
0#
#2930
b10 *
b11101000 +
1#
#2940
0#
#2950
b11 *
b111010000 +
1#
#2960
0#
#2970
b100 *
b1110100000 +
1#
#2980
0#
#2990
b101 *
b101001000000 +
1#
#3000
0#
#3010
b110 *
b1010010000000 +
1#
#3020
0#
#3030
b111 *
b10110000000000 +
1#
#3040
0#
#3050
b1000 *
b1000101100000000 +
1#
#3060
0#
#3070
b100010110 "
b100010110 (
b1001 *
b10001011000000000 )
b10001011000000000 +
1#
b1110101 !
b1110101 '
b1110101 $
b10000 &
#3080
0#
#3090
b1 *
b1110101 +
1#
#3100
0#
#3110
b10 *
b11101010 +
1#
#3120
0#
#3130
b11 *
b111010100 +
1#
#3140
0#
#3150
b100 *
b1110101000 +
1#
#3160
0#
#3170
b101 *
b101001010000 +
1#
#3180
0#
#3190
b110 *
b1010010100000 +
1#
#3200
0#
#3210
b111 *
b10110001000000 +
1#
#3220
0#
#3230
b1000 *
b1000101110000000 +
1#
#3240
0#
#3250
b100010111 "
b100010111 (
b1001 *
b10001011100000000 )
b10001011100000000 +
1#
b1110110 !
b1110110 '
b1110110 $
b10001 &
#3260
0#
#3270
b1 *
b1110110 +
1#
#3280
0#
#3290
b10 *
b11101100 +
1#
#3300
0#
#3310
b11 *
b111011000 +
1#
#3320
0#
#3330
b100 *
b1110110000 +
1#
#3340
0#
#3350
b101 *
b101001100000 +
1#
#3360
0#
#3370
b110 *
b1010011000000 +
1#
#3380
0#
#3390
b111 *
b10110010000000 +
1#
#3400
0#
#3410
b1000 *
b1000110000000000 +
1#
#3420
0#
#3430
b100011000 "
b100011000 (
b1001 *
b10001100000000000 )
b10001100000000000 +
1#
b1110111 !
b1110111 '
b1110111 $
b10010 &
#3440
0#
#3450
b1 *
b1110111 +
1#
#3460
0#
#3470
b10 *
b11101110 +
1#
#3480
0#
#3490
b11 *
b111011100 +
1#
#3500
0#
#3510
b100 *
b1110111000 +
1#
#3520
0#
#3530
b101 *
b101001110000 +
1#
#3540
0#
#3550
b110 *
b1010011100000 +
1#
#3560
0#
#3570
b111 *
b10110011000000 +
1#
#3580
0#
#3590
b1000 *
b1000110010000000 +
1#
#3600
0#
#3610
b100011001 "
b100011001 (
b1001 *
b10001100100000000 )
b10001100100000000 +
1#
b1111000 !
b1111000 '
b1111000 $
b10011 &
#3620
0#
#3630
b1 *
b1111000 +
1#
#3640
0#
#3650
b10 *
b11110000 +
1#
#3660
0#
#3670
b11 *
b111100000 +
1#
#3680
0#
#3690
b100 *
b1111000000 +
1#
#3700
0#
#3710
b101 *
b101010000000 +
1#
#3720
0#
#3730
b110 *
b1100000000000 +
1#
#3740
0#
#3750
b111 *
b11000000000000 +
1#
#3760
0#
#3770
b1000 *
b1001000000000000 +
1#
#3780
0#
#3790
b100100000 "
b100100000 (
b1001 *
b10010000000000000 )
b10010000000000000 +
1#
b1111001 !
b1111001 '
b1111001 $
b10100 &
#3800
0#
#3810
b1 *
b1111001 +
1#
#3820
0#
#3830
b10 *
b11110010 +
1#
#3840
0#
#3850
b11 *
b111100100 +
1#
#3860
0#
#3870
b100 *
b1111001000 +
1#
#3880
0#
#3890
b101 *
b101010010000 +
1#
#3900
0#
#3910
b110 *
b1100000100000 +
1#
#3920
0#
#3930
b111 *
b11000001000000 +
1#
#3940
0#
#3950
b1000 *
b1001000010000000 +
1#
#3960
0#
#3970
b100100001 "
b100100001 (
b1001 *
b10010000100000000 )
b10010000100000000 +
1#
b1111010 !
b1111010 '
b1111010 $
b10101 &
#3980
0#
#3990
b1 *
b1111010 +
1#
#4000
0#
#4010
b10 *
b11110100 +
1#
#4020
0#
#4030
b11 *
b111101000 +
1#
#4040
0#
#4050
b100 *
b1111010000 +
1#
#4060
0#
#4070
b101 *
b101010100000 +
1#
#4080
0#
#4090
b110 *
b1100001000000 +
1#
#4100
0#
#4110
b111 *
b11000010000000 +
1#
#4120
0#
#4130
b1000 *
b1001000100000000 +
1#
#4140
0#
#4150
b100100010 "
b100100010 (
b1001 *
b10010001000000000 )
b10010001000000000 +
1#
b1111011 !
b1111011 '
b1111011 $
b10110 &
#4160
0#
#4170
b1 *
b1111011 +
1#
#4180
0#
#4190
b10 *
b11110110 +
1#
#4200
0#
#4210
b11 *
b111101100 +
1#
#4220
0#
#4230
b100 *
b1111011000 +
1#
#4240
0#
#4250
b101 *
b101010110000 +
1#
#4260
0#
#4270
b110 *
b1100001100000 +
1#
#4280
0#
#4290
b111 *
b11000011000000 +
1#
#4300
0#
#4310
b1000 *
b1001000110000000 +
1#
#4320
0#
#4330
b100100011 "
b100100011 (
b1001 *
b10010001100000000 )
b10010001100000000 +
1#
b1111100 !
b1111100 '
b1111100 $
b10111 &
#4340
0#
#4350
b1 *
b1111100 +
1#
#4360
0#
#4370
b10 *
b11111000 +
1#
#4380
0#
#4390
b11 *
b111110000 +
1#
#4400
0#
#4410
b100 *
b1111100000 +
1#
#4420
0#
#4430
b101 *
b101011000000 +
1#
#4440
0#
#4450
b110 *
b1100010000000 +
1#
#4460
0#
#4470
b111 *
b11000100000000 +
1#
#4480
0#
#4490
b1000 *
b1001001000000000 +
1#
#4500
0#
#4510
b100100100 "
b100100100 (
b1001 *
b10010010000000000 )
b10010010000000000 +
1#
b1111101 !
b1111101 '
b1111101 $
b11000 &
#4520
0#
#4530
b1 *
b1111101 +
1#
#4540
0#
#4550
b10 *
b11111010 +
1#
#4560
0#
#4570
b11 *
b111110100 +
1#
#4580
0#
#4590
b100 *
b1111101000 +
1#
#4600
0#
#4610
b101 *
b101011010000 +
1#
#4620
0#
#4630
b110 *
b1100010100000 +
1#
#4640
0#
#4650
b111 *
b11000101000000 +
1#
#4660
0#
#4670
b1000 *
b1001001010000000 +
1#
#4680
0#
#4690
b100100101 "
b100100101 (
b1001 *
b10010010100000000 )
b10010010100000000 +
1#
b1111110 !
b1111110 '
b1111110 $
b11001 &
#4700
0#
#4710
b1 *
b1111110 +
1#
#4720
0#
#4730
b10 *
b11111100 +
1#
#4740
0#
#4750
b11 *
b111111000 +
1#
#4760
0#
#4770
b100 *
b1111110000 +
1#
#4780
0#
#4790
b101 *
b101011100000 +
1#
#4800
0#
#4810
b110 *
b1100011000000 +
1#
#4820
0#
#4830
b111 *
b11000110000000 +
1#
#4840
0#
#4850
b1000 *
b1001001100000000 +
1#
#4860
0#
#4870
b100100110 "
b100100110 (
b1001 *
b10010011000000000 )
b10010011000000000 +
1#
b1111111 !
b1111111 '
b1111111 $
b11010 &
#4880
0#
#4890
b1 *
b1111111 +
1#
#4900
0#
#4910
b10 *
b11111110 +
1#
#4920
0#
#4930
b11 *
b111111100 +
1#
#4940
0#
#4950
b100 *
b1111111000 +
1#
#4960
0#
#4970
b101 *
b101011110000 +
1#
#4980
0#
#4990
b110 *
b1100011100000 +
1#
#5000
0#
#5010
b111 *
b11000111000000 +
1#
#5020
0#
#5030
b1000 *
b1001001110000000 +
1#
#5040
0#
#5050
b100100111 "
b100100111 (
b1001 *
b10010011100000000 )
b10010011100000000 +
1#
b10000000 !
b10000000 '
b10000000 $
b11011 &
#5060
0#
#5070
b1 *
b10000000 +
1#
#5080
0#
#5090
b10 *
b100000000 +
1#
#5100
0#
#5110
b11 *
b1000000000 +
1#
#5120
0#
#5130
b100 *
b10000000000 +
1#
#5140
0#
#5150
b101 *
b101100000000 +
1#
#5160
0#
#5170
b110 *
b1100100000000 +
1#
#5180
0#
#5190
b111 *
b11001000000000 +
1#
#5200
0#
#5210
b1000 *
b1001010000000000 +
1#
#5220
0#
#5230
b100101000 "
b100101000 (
b1001 *
b10010100000000000 )
b10010100000000000 +
1#
b10000001 !
b10000001 '
b10000001 $
b11100 &
#5240
0#
#5250
b1 *
b10000001 +
1#
#5260
0#
#5270
b10 *
b100000010 +
1#
#5280
0#
#5290
b11 *
b1000000100 +
1#
#5300
0#
#5310
b100 *
b10000001000 +
1#
#5320
0#
#5330
b101 *
b101100010000 +
1#
#5340
0#
#5350
b110 *
b1100100100000 +
1#
#5360
0#
#5370
b111 *
b11001001000000 +
1#
#5380
0#
#5390
b1000 *
b1001010010000000 +
1#
#5400
0#
#5410
b100101001 "
b100101001 (
b1001 *
b10010100100000000 )
b10010100100000000 +
1#
b10000010 !
b10000010 '
b10000010 $
b11101 &
#5420
0#
#5430
b1 *
b10000010 +
1#
#5440
0#
#5450
b10 *
b100000100 +
1#
#5460
0#
#5470
b11 *
b1000001000 +
1#
#5480
0#
#5490
b100 *
b10000010000 +
1#
#5500
0#
#5510
b101 *
b101100100000 +
1#
#5520
0#
#5530
b110 *
b1100101000000 +
1#
#5540
0#
#5550
b111 *
b11001010000000 +
1#
#5560
0#
#5570
b1000 *
b1001100000000000 +
1#
#5580
0#
#5590
b100110000 "
b100110000 (
b1001 *
b10011000000000000 )
b10011000000000000 +
1#
b10000011 !
b10000011 '
b10000011 $
b11110 &
#5600
0#
#5610
b1 *
b10000011 +
1#
#5620
0#
#5630
b10 *
b100000110 +
1#
#5640
0#
#5650
b11 *
b1000001100 +
1#
#5660
0#
#5670
b100 *
b10000011000 +
1#
#5680
0#
#5690
b101 *
b101100110000 +
1#
#5700
0#
#5710
b110 *
b1100101100000 +
1#
#5720
0#
#5730
b111 *
b11001011000000 +
1#
#5740
0#
#5750
b1000 *
b1001100010000000 +
1#
#5760
0#
#5770
b100110001 "
b100110001 (
b1001 *
b10011000100000000 )
b10011000100000000 +
1#
b10000100 !
b10000100 '
b10000100 $
b11111 &
#5780
0#
#5790
b1 *
b10000100 +
1#
#5800
0#
#5810
b10 *
b100001000 +
1#
#5820
0#
#5830
b11 *
b1000010000 +
1#
#5840
0#
#5850
b100 *
b10000100000 +
1#
#5860
0#
#5870
b101 *
b101101000000 +
1#
#5880
0#
#5890
b110 *
b1100110000000 +
1#
#5900
0#
#5910
b111 *
b11001100000000 +
1#
#5920
0#
#5930
b1000 *
b1001100100000000 +
1#
#5940
0#
#5950
b100110010 "
b100110010 (
b1001 *
b10011001000000000 )
b10011001000000000 +
1#
b10000101 !
b10000101 '
b10000101 $
b100000 &
#5960
0#
#5970
b1 *
b10000101 +
1#
#5980
0#
#5990
b10 *
b100001010 +
1#
#6000
0#
#6010
b11 *
b1000010100 +
1#
#6020
0#
#6030
b100 *
b10000101000 +
1#
#6040
0#
#6050
b101 *
b101101010000 +
1#
#6060
0#
#6070
b110 *
b1100110100000 +
1#
#6080
0#
#6090
b111 *
b11001101000000 +
1#
#6100
0#
#6110
b1000 *
b1001100110000000 +
1#
#6120
0#
#6130
b100110011 "
b100110011 (
b1001 *
b10011001100000000 )
b10011001100000000 +
1#
b10000110 !
b10000110 '
b10000110 $
b100001 &
#6140
0#
#6150
b1 *
b10000110 +
1#
#6160
0#
#6170
b10 *
b100001100 +
1#
#6180
0#
#6190
b11 *
b1000011000 +
1#
#6200
0#
#6210
b100 *
b10000110000 +
1#
#6220
0#
#6230
b101 *
b101101100000 +
1#
#6240
0#
#6250
b110 *
b1100111000000 +
1#
#6260
0#
#6270
b111 *
b11001110000000 +
1#
#6280
0#
#6290
b1000 *
b1001101000000000 +
1#
#6300
0#
#6310
b100110100 "
b100110100 (
b1001 *
b10011010000000000 )
b10011010000000000 +
1#
b10000111 !
b10000111 '
b10000111 $
b100010 &
#6320
0#
#6330
b1 *
b10000111 +
1#
#6340
0#
#6350
b10 *
b100001110 +
1#
#6360
0#
#6370
b11 *
b1000011100 +
1#
#6380
0#
#6390
b100 *
b10000111000 +
1#
#6400
0#
#6410
b101 *
b101101110000 +
1#
#6420
0#
#6430
b110 *
b1100111100000 +
1#
#6440
0#
#6450
b111 *
b11001111000000 +
1#
#6460
0#
#6470
b1000 *
b1001101010000000 +
1#
#6480
0#
#6490
b100110101 "
b100110101 (
b1001 *
b10011010100000000 )
b10011010100000000 +
1#
b10001000 !
b10001000 '
b10001000 $
b100011 &
#6500
0#
#6510
b1 *
b10001000 +
1#
#6520
0#
#6530
b10 *
b100010000 +
1#
#6540
0#
#6550
b11 *
b1000100000 +
1#
#6560
0#
#6570
b100 *
b10001000000 +
1#
#6580
0#
#6590
b101 *
b101110000000 +
1#
#6600
0#
#6610
b110 *
b1101000000000 +
1#
#6620
0#
#6630
b111 *
b11010000000000 +
1#
#6640
0#
#6650
b1000 *
b1001101100000000 +
1#
#6660
0#
#6670
b100110110 "
b100110110 (
b1001 *
b10011011000000000 )
b10011011000000000 +
1#
b10001001 !
b10001001 '
b10001001 $
b100100 &
#6680
0#
#6690
b1 *
b10001001 +
1#
#6700
0#
#6710
b10 *
b100010010 +
1#
#6720
0#
#6730
b11 *
b1000100100 +
1#
#6740
0#
#6750
b100 *
b10001001000 +
1#
#6760
0#
#6770
b101 *
b101110010000 +
1#
#6780
0#
#6790
b110 *
b1101000100000 +
1#
#6800
0#
#6810
b111 *
b11010001000000 +
1#
#6820
0#
#6830
b1000 *
b1001101110000000 +
1#
#6840
0#
#6850
b100110111 "
b100110111 (
b1001 *
b10011011100000000 )
b10011011100000000 +
1#
b10001010 !
b10001010 '
b10001010 $
b100101 &
#6860
0#
#6870
b1 *
b10001010 +
1#
#6880
0#
#6890
b10 *
b100010100 +
1#
#6900
0#
#6910
b11 *
b1000101000 +
1#
#6920
0#
#6930
b100 *
b10001010000 +
1#
#6940
0#
#6950
b101 *
b101110100000 +
1#
#6960
0#
#6970
b110 *
b1101001000000 +
1#
#6980
0#
#6990
b111 *
b11010010000000 +
1#
#7000
0#
#7010
b1000 *
b1001110000000000 +
1#
#7020
0#
#7030
b100111000 "
b100111000 (
b1001 *
b10011100000000000 )
b10011100000000000 +
1#
b10001011 !
b10001011 '
b10001011 $
b100110 &
#7040
0#
#7050
b1 *
b10001011 +
1#
#7060
0#
#7070
b10 *
b100010110 +
1#
#7080
0#
#7090
b11 *
b1000101100 +
1#
#7100
0#
#7110
b100 *
b10001011000 +
1#
#7120
0#
#7130
b101 *
b101110110000 +
1#
#7140
0#
#7150
b110 *
b1101001100000 +
1#
#7160
0#
#7170
b111 *
b11010011000000 +
1#
#7180
0#
#7190
b1000 *
b1001110010000000 +
1#
#7200
0#
#7210
b100111001 "
b100111001 (
b1001 *
b10011100100000000 )
b10011100100000000 +
1#
b10001100 !
b10001100 '
b10001100 $
b100111 &
#7220
0#
#7230
b1 *
b10001100 +
1#
#7240
0#
#7250
b10 *
b100011000 +
1#
#7260
0#
#7270
b11 *
b1000110000 +
1#
#7280
0#
#7290
b100 *
b10001100000 +
1#
#7300
0#
#7310
b101 *
b101111000000 +
1#
#7320
0#
#7330
b110 *
b1101010000000 +
1#
#7340
0#
#7350
b111 *
b11100000000000 +
1#
#7360
0#
#7370
b1000 *
b1010000000000000 +
1#
#7380
0#
#7390
b101000000 "
b101000000 (
b1001 *
b10100000000000000 )
b10100000000000000 +
1#
b10001101 !
b10001101 '
b10001101 $
b101000 &
#7400
0#
#7410
b1 *
b10001101 +
1#
#7420
0#
#7430
b10 *
b100011010 +
1#
#7440
0#
#7450
b11 *
b1000110100 +
1#
#7460
0#
#7470
b100 *
b10001101000 +
1#
#7480
0#
#7490
b101 *
b101111010000 +
1#
#7500
0#
#7510
b110 *
b1101010100000 +
1#
#7520
0#
#7530
b111 *
b11100001000000 +
1#
#7540
0#
#7550
b1000 *
b1010000010000000 +
1#
#7560
0#
#7570
b101000001 "
b101000001 (
b1001 *
b10100000100000000 )
b10100000100000000 +
1#
b10001110 !
b10001110 '
b10001110 $
b101001 &
#7580
0#
#7590
b1 *
b10001110 +
1#
#7600
0#
#7610
b10 *
b100011100 +
1#
#7620
0#
#7630
b11 *
b1000111000 +
1#
#7640
0#
#7650
b100 *
b10001110000 +
1#
#7660
0#
#7670
b101 *
b101111100000 +
1#
#7680
0#
#7690
b110 *
b1101011000000 +
1#
#7700
0#
#7710
b111 *
b11100010000000 +
1#
#7720
0#
#7730
b1000 *
b1010000100000000 +
1#
#7740
0#
#7750
b101000010 "
b101000010 (
b1001 *
b10100001000000000 )
b10100001000000000 +
1#
b10001111 !
b10001111 '
b10001111 $
b101010 &
#7760
0#
#7770
b1 *
b10001111 +
1#
#7780
0#
#7790
b10 *
b100011110 +
1#
#7800
0#
#7810
b11 *
b1000111100 +
1#
#7820
0#
#7830
b100 *
b10001111000 +
1#
#7840
0#
#7850
b101 *
b101111110000 +
1#
#7860
0#
#7870
b110 *
b1101011100000 +
1#
#7880
0#
#7890
b111 *
b11100011000000 +
1#
#7900
0#
#7910
b1000 *
b1010000110000000 +
1#
#7920
0#
#7930
b101000011 "
b101000011 (
b1001 *
b10100001100000000 )
b10100001100000000 +
1#
b10010000 !
b10010000 '
b10010000 $
b101011 &
#7940
0#
#7950
b1 *
b10010000 +
1#
#7960
0#
#7970
b10 *
b100100000 +
1#
#7980
0#
#7990
b11 *
b1001000000 +
1#
#8000
0#
#8010
b100 *
b10010000000 +
1#
#8020
0#
#8030
b101 *
b110000000000 +
1#
#8040
0#
#8050
b110 *
b1101100000000 +
1#
#8060
0#
#8070
b111 *
b11100100000000 +
1#
#8080
0#
#8090
b1000 *
b1010001000000000 +
1#
#8100
0#
#8110
b101000100 "
b101000100 (
b1001 *
b10100010000000000 )
b10100010000000000 +
1#
b10010001 !
b10010001 '
b10010001 $
b101100 &
#8120
0#
#8130
b1 *
b10010001 +
1#
#8140
0#
#8150
b10 *
b100100010 +
1#
#8160
0#
#8170
b11 *
b1001000100 +
1#
#8180
0#
#8190
b100 *
b10010001000 +
1#
#8200
0#
#8210
b101 *
b110000010000 +
1#
#8220
0#
#8230
b110 *
b1101100100000 +
1#
#8240
0#
#8250
b111 *
b11100101000000 +
1#
#8260
0#
