uart/Shift_Reg.v
module Shift_Reg(Serial_out, Data_reg_in, Load_shift_register, Start, Clk, Reset);
	output Serial_out;

	input [9:0] Data_reg_in;
	input Load_shift_register, Start, Clk, Reset;

	reg[3:0] Counter;
	reg[9:0] Shift_reg_data;

	
	assign Serial_out = Shift_reg_data[9];

	// Counter 
	always @(posedge Clk) begin
		if (Reset || Counter == 4'b1010 || Load_shift_register || !Start) begin 
			Counter <= 4'b0;
		end else begin
			Counter <= Counter + 1'b1;
		end
	end

	// shift register loading logic
	always @(posedge Clk) begin
		if (Reset) begin
			Shift_reg_data <= 10'bxxxxxxxxxx;
		end else begin
			if (Load_shift_register) // Start will never be on at the same time 
				Shift_reg_data <= Data_reg_in;
		end	
	end

	// shift/output logic
	always @(posedge Clk) begin
		if (!Reset) begin
			if (Start) begin
				if (Counter != 4'b0000 || Counter >= 4'b1010) //don't shift on first clk cycle since i want original MSB, and stop shifting when byte is finished
					Shift_reg_data = Shift_reg_data << 1;
			end
		end 
	end


endmodule

// module Shift_Reg_tb();
	
// 	parameter PERIOD = 10;

// 	reg Clk, Reset;
// 	wire Clk_w, Reset_w; 
	
// 	wire Serial_out;

// 	reg Load_shift_register, Start;
// 	wire Load_shift_register_w, Start_w;

// 	reg [9:0] Data_reg_in;
// 	wire[9:0] Data_reg_in_w;


// 	assign Clk_w = Clk;
// 	assign Reset_w = Reset;
// 	assign Load_shift_register_w = Load_shift_register;
// 	assign Data_reg_in_w = Data_reg_in;
// 	assign Start_w = Start; 

// 	Shift_Reg dut(.Serial_out(Serial_out), .Data_reg_in(Data_reg_in_w), .Load_shift_register(Load_shift_register_w), .Start(Start_w), .Clk(Clk), .Reset(Reset));


// 	always #PERIOD Clk=~Clk;

// 	initial begin
// 		$dumpfile("Shift_Reg.vcd");
// 		$dumpvars(0, dut);
// 	end

// 	initial begin

// 		#(2*PERIOD);

// 		Reset = 1; Load_shift_register = 0; Data_reg_in = 10'b0111111111; Start = 0; Clk = 0; #(2*PERIOD);
// 		#(2*PERIOD);
// 		#(2*PERIOD);
// 		#(2*PERIOD); 
// 		Reset = 0;
// 		#(2*PERIOD);
// 		#(2*PERIOD);
// 		Load_shift_register = 1;
// 		#(2*PERIOD);
// 		Start = 1; Load_shift_register = 0; // new data at least 10 cycles after start
// 		#(2*PERIOD);
// 		#(2*PERIOD);
// 		#(2*PERIOD);
// 		#(2*PERIOD);
// 		#(2*PERIOD);
// 		#(2*PERIOD);
// 		#(2*PERIOD);
// 		#(2*PERIOD);
// 		#(2*PERIOD);
// 		#(2*PERIOD);
// 		Data_reg_in = 10'b1010101010; 
// 		#(2*PERIOD);
// 		#(2*PERIOD);
// 		Start = 0; Load_shift_register = 1; // always make sure Start and Load_shift_register are not equal
// 		#(2*PERIOD);
// 		#(2*PERIOD);
// 		#(2*PERIOD);
// 		Start = 1; Load_shift_register = 0;
// 		#(2*PERIOD);
// 		#(2*PERIOD);
// 		#(2*PERIOD);
// 		#(2*PERIOD);
// 		#(2*PERIOD);
// 		#(2*PERIOD);
// 		#(2*PERIOD);
// 		#(2*PERIOD);
// 		#(2*PERIOD);
// 		#(2*PERIOD);
// 		$finish;
// 	end
// endmodule

uart/Data_Reg.v
module Data_Reg(Byte_pckg_out, Data_bus, Clk, Reset, Load_XMT_register);
	output [9:0] Byte_pckg_out;

	input [7:0] Data_bus;
	input Clk, Reset, Load_XMT_register;

	assign Byte_pckg_out = Byte_pckg;

	reg [9:0] Byte_pckg;

	always @(posedge Clk) begin
		if (Reset) begin
			Byte_pckg <= 10'b0000000001;
		end	else begin
			if (Load_XMT_register) 
				Byte_pckg[8:1] = Data_bus;
			else
				Byte_pckg[8:1] = 8'b0;
		end
	end

endmodule 


// module Data_Reg_tb();
	
// 	parameter PERIOD = 10;

// 	reg Clk, Reset, Load_XMT_register;
// 	wire Clk_w, Reset_w, Load_XMT_register_w;
	
// 	reg [7:0] Data_bus;
// 	wire[7:0] Data_bus_w;

// 	wire[9:0] Byte_pckg_out;

// 	assign Clk_w = Clk;
// 	assign Reset_w = Reset;
// 	assign Load_XMT_register_w = Load_XMT_register;
// 	assign Data_bus_w = Data_bus; 


// 	Data_Reg dut(.Byte_pckg_out(Byte_pckg_out), .Data_bus(Data_bus_w), .Clk(Clk_w), .Reset(Reset_w), .Load_XMT_register(Load_XMT_register_w));


// 	always #PERIOD Clk=~Clk;

// 	initial begin
// 		$dumpfile("Data_Reg.vcd");
// 		$dumpvars(0, dut);
// 	end

// 	initial begin
// 		Reset = 1; Load_XMT_register = 0; Data_bus = 8'b11111111; Clk = 0; #(2*PERIOD);
// 		#(2*PERIOD);
// 		#(2*PERIOD);
// 		#(2*PERIOD); 
// 		Reset = 0;
// 		#(2*PERIOD);
// 		#(2*PERIOD);
// 		Load_XMT_register = 1;
// 		#(2*PERIOD);
// 		#(2*PERIOD);
// 		#(2*PERIOD);
// 		#(2*PERIOD);
// 		Load_XMT_register = 0;
// 		#(2*PERIOD);
// 		#(2*PERIOD);
// 		#(2*PERIOD);
// 		$finish;
// 	end
// endmodule

uart/Trans_Contr.v
`include "Data_Reg.v"
`include "Shift_Reg.v"

module Trans_Contr(Serial_out, Clk, Reset, Byte_ready, T_byte, Data_in);
	output Serial_out;
	input Clk, Reset;
	input Byte_ready, T_byte; // Byte_ready for signalling loading the shift reg
								// T_byte used to actually signal a transmit operation

	input [7:0] Data_in;							
	// status registers
	reg Start, /*Clear, */Load_shift_register, Load_XMT_register;
	reg [3:0] Counter;

	wire Start_w, Load_shift_register_w, Load_XMT_register_w;

	// module hookup wires
	wire [9:0] Byte_pckg_out_Data_reg_in;


	parameter [1:0]	Idle = 2'b00;
	parameter [1:0]	Loading = 2'b01;
	parameter [1:0]	Transmitting = 2'b10;
	parameter [1:0]	Clearing = 2'b11;
	//, Loading = 2'b01, Transmitting = 2'b10; Clearing = 2'b11; 
	
	reg[1:0] ps, ns;

	Data_Reg data_reg(.Byte_pckg_out(Byte_pckg_out_Data_reg_in), .Data_bus(Data_in), .Clk(Clk), .Reset(Reset), .Load_XMT_register(Load_XMT_register_w));
	Shift_Reg shift_reg(.Serial_out(Serial_out), .Data_reg_in(Byte_pckg_out_Data_reg_in), .Load_shift_register(Load_shift_register_w), .Start(Start_w), .Clk(Clk), .Reset(Reset));


	assign Start_w = Start;
	assign Load_shift_register_w = Load_shift_register;
	assign Load_XMT_register_w = Load_XMT_register;



	always @(posedge Clk) begin
		if (Reset) begin
			ps <= Idle;
			ns <= Idle;
			Counter <= 4'b0;
		end else begin
			case (ps)
				Idle: //----------------------------------------------------------------IDLE----------------------------------
					if (Byte_ready) begin
						ns <= Loading;
						Load_XMT_register <= 1;
						Load_shift_register <= 1;
					end else begin
						ns = Idle;
						Load_shift_register <= 0;
						Load_XMT_register <= 0;
						Start <= 0;		
					end 
				Loading: //------------------------------------------------------------LOADING--------------------------------
					if (T_byte) begin
						ns <= Transmitting;
						Counter <= 4'b0; 
					end else begin 
						if (Load_shift_register == 1'b0) begin
							ns <= 2'b00;
							//Load_shift_register <= 0;
							Load_XMT_register <= 0;
							Start <= 0;
						end else begin

							ns <= Loading;
							//Load_shift_register <= 1;
							Load_XMT_register <= 1;
							Start <= 0;	
						end
					end
				Transmitting: //-------------------------------------------------------TRANSMITTING----------------------------
					if (Counter == 4'b1100) begin // unsure about when to set counter rn
						ns <= Clearing;
						Load_shift_register <= 0; // these two loads were moved from Clearing stage to hit it a cycle before
						Load_XMT_register <= 0;
						Start <= 0;
						
					end else begin
						ns <= Transmitting;
						Counter <= Counter + 1'b1;
						Load_shift_register <= 0;
						Load_XMT_register <= 1;
						Start <= 1;
					end
				Clearing: // ---------------------------------------------------------CLEARING-----------------------------------
					begin
						//Counter <= 4'b0;
						ns <= Idle;
						Load_XMT_register <= 0;
						Start <= 0;
					end
			endcase
		end
	end

	always @(posedge Clk) begin
		if (Reset) begin
			ps <= Idle;
			ns <= Idle;
		end else begin
			ps <= ns;
		end
	end

endmodule

module Trans_Contr_tb();
	
	parameter PERIOD = 10;

	reg Clk, Reset, Byte_ready, T_byte;
	wire Clk_w, Reset_w, Byte_ready_w, T_byte_w;
	
	reg [7:0] Data_bus;
	wire[7:0] Data_bus_w;

	wire Serial_out;

	assign Clk_w = Clk;
	assign Reset_w = Reset;
	assign Byte_ready_w = Byte_ready;
	assign T_byte_w = T_byte;

	assign Data_bus_w = Data_bus; 


	Trans_Contr dut(.Serial_out(Serial_out), .Clk(Clk_w), .Reset(Reset_w), .Byte_ready(Byte_ready_w), .T_byte(T_byte_w), .Data_in(Data_bus_w));


	always #PERIOD Clk=~Clk;

	initial begin
		$dumpfile("Trans_Contr.vcd");
		$dumpvars(0, dut);
		#(200*PERIOD);
		$finish;
	end

	initial begin
		Reset = 1; Byte_ready = 0; T_byte = 0; Clk = 0; Data_bus = 8'b11111111; #(2*PERIOD);
		#(2*PERIOD); 
		#(2*PERIOD);
		Reset = 0;
		#(2*PERIOD);
		#(2*PERIOD);
		Byte_ready = 1;
		#(2*PERIOD);
		#(2*PERIOD);
		T_byte = 1;
		#(14*2*PERIOD);
		T_byte = 0; Byte_ready = 0; Data_bus = 8'b10101010;
		#(2*PERIOD);
		#(2*PERIOD);
		#(2*PERIOD);
		#(2*PERIOD); 
		Byte_ready = 1;
		#(2*PERIOD);
		#(2*PERIOD);
		T_byte = 1;
		#(14*2*PERIOD);
		T_byte = 0; Byte_ready = 0;
		#(2*PERIOD);
		#(2*PERIOD);
		#(2*PERIOD);
		#(2*PERIOD);
		// #(2*PERIOD);
		// #(2*PERIOD);
		// #(2*PERIOD);
		// #(2*PERIOD);
		// #(2*PERIOD);
		 #(20*PERIOD);
		$finish;
	end
endmodule

uart/Trans_Contr.vcd
$date
	Tue Sep 24 13:54:02 2019
$end
$version
	Icarus Verilog
$end
$timescale
	1s
$end
$scope module Trans_Contr_tb $end
$scope module dut $end
$var wire 1 ! Byte_ready $end
$var wire 1 " Clk $end
$var wire 8 # Data_in [7:0] $end
$var wire 1 $ Load_XMT_register_w $end
$var wire 1 % Load_shift_register_w $end
$var wire 1 & Reset $end
$var wire 1 ' Start_w $end
$var wire 1 ( T_byte $end
$var wire 1 ) Serial_out $end
$var wire 10 * Byte_pckg_out_Data_reg_in [9:0] $end
$var reg 4 + Counter [3:0] $end
$var reg 1 , Load_XMT_register $end
$var reg 1 - Load_shift_register $end
$var reg 1 . Start $end
$var reg 2 / ns [1:0] $end
$var reg 2 0 ps [1:0] $end
$scope module data_reg $end
$var wire 10 1 Byte_pckg_out [9:0] $end
$var wire 1 " Clk $end
$var wire 8 2 Data_bus [7:0] $end
$var wire 1 $ Load_XMT_register $end
$var wire 1 & Reset $end
$var reg 10 3 Byte_pckg [9:0] $end
$upscope $end
$scope module shift_reg $end
$var wire 1 " Clk $end
$var wire 10 4 Data_reg_in [9:0] $end
$var wire 1 % Load_shift_register $end
$var wire 1 & Reset $end
$var wire 1 ' Start $end
$var wire 1 ) Serial_out $end
$var reg 4 5 Counter [3:0] $end
$var reg 10 6 Shift_reg_data [9:0] $end
$upscope $end
$upscope $end
$upscope $end
$enddefinitions $end
#0
$dumpvars
bx 6
bx 5
bx 4
bx 3
b11111111 2
bx 1
bx 0
bx /
x.
x-
x,
bx +
bx *
x)
0(
x'
1&
x%
x$
b11111111 #
0"
0!
$end
#10
b1 *
b1 1
b1 4
b1 3
b0 5
b0 +
b0 /
b0 0
1"
#20
0"
#30
1"
#40
0"
#50
1"
#60
0"
0&
#70
0'
0.
0$
0,
0%
0-
b1 5
1"
#80
0"
#90
b0 5
1"
#100
0"
1!
#110
1%
1-
1$
1,
b1 /
1"
#120
0"
#130
0)
b1 6
b1 0
b111111111 *
b111111111 1
b111111111 4
b111111111 3
1"
#140
0"
1(
#150
b10 /
b111111111 6
1"
#160
0"
#170
b10 0
1"
#180
0"
#190
1'
1.
0%
0-
b1 +
1"
#200
0"
#210
b1 5
b10 +
1"
#220
0"
#230
b11 +
b10 5
1)
b1111111110 6
1"
#240
0"
#250
b11 5
b100 +
b1111111100 6
1"
#260
0"
#270
b101 +
b100 5
b1111111000 6
1"
#280
0"
#290
b101 5
b110 +
b1111110000 6
1"
#300
0"
#310
b111 +
b110 5
b1111100000 6
1"
#320
0"
#330
b111 5
b1000 +
b1111000000 6
1"
#340
0"
#350
b1001 +
b1000 5
b1110000000 6
1"
#360
0"
#370
b1001 5
b1010 +
b1100000000 6
1"
#380
0"
#390
b1011 +
b1010 5
b1000000000 6
1"
#400
0"
#410
b0 5
b1100 +
0)
b0 6
1"
#420
0"
b10101010 #
b10101010 2
0!
0(
#430
0'
0.
0$
0,
b11 /
b1 5
b101010101 *
b101010101 1
b101010101 4
b101010101 3
1"
#440
0"
#450
b0 5
b11 0
b1 *
b1 1
b1 4
b1 3
1"
#460
0"
#470
b0 /
1"
#480
0"
#490
b0 0
1"
#500
0"
1!
#510
1%
1-
1$
1,
b1 /
1"
#520
0"
#530
b1 6
b1 0
b101010101 *
b101010101 1
b101010101 4
b101010101 3
1"
#540
0"
1(
#550
b0 +
b10 /
b101010101 6
1"
#560
0"
#570
b10 0
1"
#580
0"
#590
1'
1.
0%
0-
b1 +
1"
#600
0"
#610
b1 5
b10 +
1"
#620
0"
#630
b11 +
b10 5
1)
b1010101010 6
1"
#640
0"
#650
b11 5
b100 +
0)
b101010100 6
1"
#660
0"
#670
b101 +
b100 5
1)
b1010101000 6
1"
#680
0"
#690
b101 5
b110 +
0)
b101010000 6
1"
#700
0"
#710
b111 +
b110 5
1)
b1010100000 6
1"
#720
0"
#730
b111 5
b1000 +
0)
b101000000 6
1"
#740
0"
#750
b1001 +
b1000 5
1)
b1010000000 6
1"
#760
0"
#770
b1001 5
b1010 +
0)
b100000000 6
1"
#780
0"
#790
b1011 +
b1010 5
1)
b1000000000 6
1"
#800
0"
#810
b0 5
b1100 +
0)
b0 6
1"
#820
0"
0!
0(
#830
0'
0.
0$
0,
b11 /
b1 5
1"
#840
0"
#850
b0 5
b11 0
b1 *
b1 1
b1 4
b1 3
1"
#860
0"
#870
b0 /
1"
#880
0"
#890
b0 0
1"
