uart/Shift_Reg.v
module Shift_Reg(Serial_out, Data_reg_in, Load_shift_register, Start, Clk, Reset);
	output Serial_out;

	input [9:0] Data_reg_in;
	input Load_shift_register, Start, Clk, Reset;

	reg[3:0] Counter;
	reg[9:0] Shift_reg_data;

	
	assign Serial_out = Shift_reg_data[9];

	// Counter 
	always @(posedge Clk) begin
		if (Reset || Counter == 4'b1010 || Load_shift_register || !Start) begin 
			Counter <= 4'b0;
		end else begin
			Counter <= Counter + 1'b1;
		end
	end

	// shift register loading logic
	always @(posedge Clk) begin
		if (Reset) begin
			Shift_reg_data <= 10'bxxxxxxxxxx;
		end else begin
			if (Load_shift_register) // Start will never be on at the same time 
				Shift_reg_data <= Data_reg_in;
		end	
	end

	// shift/output logic
	always @(posedge Clk) begin
		if (!Reset) begin
			if (Start) begin
				if (Counter != 4'b0000 || Counter >= 4'b1010) //don't shift on first clk cycle since i want original MSB, and stop shifting when byte is finished
					Shift_reg_data = Shift_reg_data << 1;
			end
		end 
	end


endmodule

// module Shift_Reg_tb();
	
// 	parameter PERIOD = 10;

// 	reg Clk, Reset;
// 	wire Clk_w, Reset_w; 
	
// 	wire Serial_out;

// 	reg Load_shift_register, Start;
// 	wire Load_shift_register_w, Start_w;

// 	reg [9:0] Data_reg_in;
// 	wire[9:0] Data_reg_in_w;


// 	assign Clk_w = Clk;
// 	assign Reset_w = Reset;
// 	assign Load_shift_register_w = Load_shift_register;
// 	assign Data_reg_in_w = Data_reg_in;
// 	assign Start_w = Start; 

// 	Shift_Reg dut(.Serial_out(Serial_out), .Data_reg_in(Data_reg_in_w), .Load_shift_register(Load_shift_register_w), .Start(Start_w), .Clk(Clk), .Reset(Reset));


// 	always #PERIOD Clk=~Clk;

// 	initial begin
// 		$dumpfile("Shift_Reg.vcd");
// 		$dumpvars(0, dut);
// 	end

// 	initial begin

// 		#(2*PERIOD);

// 		Reset = 1; Load_shift_register = 0; Data_reg_in = 10'b0111111111; Start = 0; Clk = 0; #(2*PERIOD);
// 		#(2*PERIOD);
// 		#(2*PERIOD);
// 		#(2*PERIOD); 
// 		Reset = 0;
// 		#(2*PERIOD);
// 		#(2*PERIOD);
// 		Load_shift_register = 1;
// 		#(2*PERIOD);
// 		Start = 1; Load_shift_register = 0; // new data at least 10 cycles after start
// 		#(2*PERIOD);
// 		#(2*PERIOD);
// 		#(2*PERIOD);
// 		#(2*PERIOD);
// 		#(2*PERIOD);
// 		#(2*PERIOD);
// 		#(2*PERIOD);
// 		#(2*PERIOD);
// 		#(2*PERIOD);
// 		#(2*PERIOD);
// 		Data_reg_in = 10'b1010101010; 
// 		#(2*PERIOD);
// 		#(2*PERIOD);
// 		Start = 0; Load_shift_register = 1; // always make sure Start and Load_shift_register are not equal
// 		#(2*PERIOD);
// 		#(2*PERIOD);
// 		#(2*PERIOD);
// 		Start = 1; Load_shift_register = 0;
// 		#(2*PERIOD);
// 		#(2*PERIOD);
// 		#(2*PERIOD);
// 		#(2*PERIOD);
// 		#(2*PERIOD);
// 		#(2*PERIOD);
// 		#(2*PERIOD);
// 		#(2*PERIOD);
// 		#(2*PERIOD);
// 		#(2*PERIOD);
// 		$finish;
// 	end
// endmodule

uart/Data_Reg.v
module Data_Reg(Byte_pckg_out, Data_bus, Clk, Reset, Load_XMT_register);
	output [9:0] Byte_pckg_out;

	input [7:0] Data_bus;
	input Clk, Reset, Load_XMT_register;

	assign Byte_pckg_out = Byte_pckg;

	reg [9:0] Byte_pckg;

	always @(posedge Clk) begin
		if (Reset) begin
			Byte_pckg <= 10'b0000000001;
		end	else begin
			if (Load_XMT_register) 
				Byte_pckg[8:1] = Data_bus;
			else
				Byte_pckg[8:1] = 8'b0;
		end
	end

endmodule 


// module Data_Reg_tb();
	
// 	parameter PERIOD = 10;

// 	reg Clk, Reset, Load_XMT_register;
// 	wire Clk_w, Reset_w, Load_XMT_register_w;
	
// 	reg [7:0] Data_bus;
// 	wire[7:0] Data_bus_w;

// 	wire[9:0] Byte_pckg_out;

// 	assign Clk_w = Clk;
// 	assign Reset_w = Reset;
// 	assign Load_XMT_register_w = Load_XMT_register;
// 	assign Data_bus_w = Data_bus; 


// 	Data_Reg dut(.Byte_pckg_out(Byte_pckg_out), .Data_bus(Data_bus_w), .Clk(Clk_w), .Reset(Reset_w), .Load_XMT_register(Load_XMT_register_w));


// 	always #PERIOD Clk=~Clk;

// 	initial begin
// 		$dumpfile("Data_Reg.vcd");
// 		$dumpvars(0, dut);
// 	end

// 	initial begin
// 		Reset = 1; Load_XMT_register = 0; Data_bus = 8'b11111111; Clk = 0; #(2*PERIOD);
// 		#(2*PERIOD);
// 		#(2*PERIOD);
// 		#(2*PERIOD); 
// 		Reset = 0;
// 		#(2*PERIOD);
// 		#(2*PERIOD);
// 		Load_XMT_register = 1;
// 		#(2*PERIOD);
// 		#(2*PERIOD);
// 		#(2*PERIOD);
// 		#(2*PERIOD);
// 		Load_XMT_register = 0;
// 		#(2*PERIOD);
// 		#(2*PERIOD);
// 		#(2*PERIOD);
// 		$finish;
// 	end
// endmodule

uart/Trans_Contr.v
`include "Data_Reg.v"
`include "Shift_Reg.v"

module Trans_Contr(Serial_out, Clk, Reset, Byte_ready, T_byte);
	output Serial_out;
	input Clk, Reset;
	input Byte_ready, T_byte; // Byte_ready for signalling loading the shift reg
								// T_byte used to actually signal a transmit operation
	// status registers
	reg Start, /*Clear, */Load_shift_register, Load_XMT_register;
	reg [3:0] Counter;

	wire Start_w, Load_shift_register_w, Load_XMT_register_w;

	// module hookup wires
	wire [9:0] Byte_pckg_out_Data_reg_in;


	parameter [1:0]	Idle = 2'b00;
	parameter [1:0]	Loading = 2'b01;
	parameter [1:0]	Transmitting = 2'b10;
	parameter [1:0]	Clearing = 2'b11;
	//, Loading = 2'b01, Transmitting = 2'b10; Clearing = 2'b11; 
	
	reg[1:0] ps, ns;

	Data_Reg data_reg(.Byte_pckg_out(Byte_pckg_out_Data_reg_in), .Data_bus(8'b01010101), .Clk(Clk), .Reset(Reset), .Load_XMT_register(Load_XMT_register_w));
	Shift_Reg shift_reg(.Serial_out(Serial_out), .Data_reg_in(Byte_pckg_out_Data_reg_in), .Load_shift_register(Load_shift_register_w), .Start(Start_w), .Clk(Clk), .Reset(Reset));


	assign Start_w = Start;
	assign Load_shift_register_w = Load_shift_register;
	assign Load_XMT_register_w = Load_XMT_register;



	always @(posedge Clk) begin
		if (Reset) begin
			ps <= Idle;
			ns <= Idle;
			Counter <= 4'b0;
		end else begin
			case (ps)
				Idle: //----------------------------------------------------------------IDLE----------------------------------
					if (Byte_ready) begin
						ns <= Loading;
						Load_XMT_register <= 1;
						Load_shift_register <= 1;
					end else begin
						ns = Idle;
						Load_shift_register <= 0;
						Load_XMT_register <= 0;
						Start <= 0;		
					end 
				Loading: //------------------------------------------------------------LOADING--------------------------------
					if (T_byte) begin
						ns <= Transmitting;
						Counter <= 4'b0; 
					end else begin 
						ns <= Loading;
						Load_shift_register <= 1;
						Load_XMT_register <= 1;
						Start <= 0;	
					end
				Transmitting: //-------------------------------------------------------TRANSMITTING----------------------------
					if (Counter == 4'b1100) begin // unsure about when to set counter rn
						ns <= Clearing;
						Counter <= 4'b0;
					end else begin
						ns <= Transmitting;
						Counter <= Counter + 1'b1;
						Load_shift_register <= 0;
						Load_XMT_register <= 1;
						Start <= 1;
					end
				Clearing: // ---------------------------------------------------------CLEARING-----------------------------------
					begin
						ns <= Idle;
						Load_shift_register <= 0;
						Load_XMT_register <= 0;
						Start <= 0;
					end
				// default:
				// 	ns = Idle;
			endcase
		end
	end

	always @(posedge Clk) begin
		if (Reset) begin
			ps <= Idle;
			ns <= Idle;
		end else begin
			ps <= ns;
		end
	end

endmodule

module Trans_Contr_tb();
	
	parameter PERIOD = 10;

	reg Clk, Reset, Byte_ready, T_byte;
	wire Clk_w, Reset_w, Byte_ready_w, T_byte_w;
	
	reg [7:0] Data_bus;
	wire[7:0] Data_bus_w;

	wire Serial_out;

	assign Clk_w = Clk;
	assign Reset_w = Reset;
	assign Byte_ready_w = Byte_ready;
	assign T_byte_w = T_byte;

	assign Data_bus_w = Data_bus; 


	Trans_Contr dut(.Serial_out(Serial_out), .Clk(Clk_w), .Reset(Reset_w), .Byte_ready(Byte_ready_w), .T_byte(T_byte_w));


	always #PERIOD Clk=~Clk;

	initial begin
		$dumpfile("Trans_Contr.vcd");
		$dumpvars(0, dut);
		#(200*PERIOD);
		$finish;
	end

	initial begin
		Reset = 1; Byte_ready = 0; T_byte = 0; Clk = 0; #(2*PERIOD);
		#(2*PERIOD); 
		#(2*PERIOD);
		Reset = 0;
		#(2*PERIOD);
		#(2*PERIOD);
		Byte_ready = 1;
		#(2*PERIOD);
		#(2*PERIOD);
		T_byte = 1;
		#(2*PERIOD);
		#(2*PERIOD);
		#(2*PERIOD);
		#(2*PERIOD);
		#(2*PERIOD);
		#(2*PERIOD);
		#(2*PERIOD);
		#(2*PERIOD);
		#(2*PERIOD);
		#(2*PERIOD);
		#(2*PERIOD);
		#(2*PERIOD);
		#(2*PERIOD);
		#(2*PERIOD);
		#(2*PERIOD);
		$finish;
	end
endmodule

uart/Trans_Contr.vcd
$date
	Tue Sep 24 01:52:29 2019
$end
$version
	Icarus Verilog
$end
$timescale
	1s
$end
$scope module Trans_Contr_tb $end
$scope module dut $end
$var wire 1 ! Byte_ready $end
$var wire 1 " Clk $end
$var wire 1 # Load_XMT_register_w $end
$var wire 1 $ Load_shift_register_w $end
$var wire 1 % Reset $end
$var wire 1 & Start_w $end
$var wire 1 ' T_byte $end
$var wire 1 ( Serial_out $end
$var wire 10 ) Byte_pckg_out_Data_reg_in [9:0] $end
$var reg 4 * Counter [3:0] $end
$var reg 1 + Load_XMT_register $end
$var reg 1 , Load_shift_register $end
$var reg 1 - Start $end
$var reg 2 . ns [1:0] $end
$var reg 2 / ps [1:0] $end
$scope module data_reg $end
$var wire 10 0 Byte_pckg_out [9:0] $end
$var wire 1 " Clk $end
$var wire 8 1 Data_bus [7:0] $end
$var wire 1 # Load_XMT_register $end
$var wire 1 % Reset $end
$var reg 10 2 Byte_pckg [9:0] $end
$upscope $end
$scope module shift_reg $end
$var wire 1 " Clk $end
$var wire 10 3 Data_reg_in [9:0] $end
$var wire 1 $ Load_shift_register $end
$var wire 1 % Reset $end
$var wire 1 & Start $end
$var wire 1 ( Serial_out $end
$var reg 4 4 Counter [3:0] $end
$var reg 10 5 Shift_reg_data [9:0] $end
$upscope $end
$upscope $end
$upscope $end
$enddefinitions $end
#0
$dumpvars
bx 5
bx 4
bx 3
bx 2
b1010101 1
bx 0
bx /
bx .
x-
x,
x+
bx *
bx )
x(
0'
x&
1%
x$
x#
0"
0!
$end
#10
b1 )
b1 0
b1 3
b1 2
b0 4
b0 *
b0 .
b0 /
1"
#20
0"
#30
1"
#40
0"
#50
1"
#60
0"
0%
#70
0&
0-
0#
0+
0$
0,
b1 4
1"
#80
0"
#90
b0 4
1"
#100
0"
1!
#110
1$
1,
1#
1+
b1 .
1"
#120
0"
#130
0(
b1 5
b1 /
b10101011 )
b10101011 0
b10101011 3
b10101011 2
1"
#140
0"
1'
#150
b10 .
b10101011 5
1"
#160
0"
#170
b10 /
1"
#180
0"
#190
1&
1-
0$
0,
b1 *
1"
#200
0"
#210
b1 4
b10 *
1"
#220
0"
#230
b11 *
b10 4
b101010110 5
1"
#240
0"
#250
b11 4
b100 *
1(
b1010101100 5
1"
#260
0"
#270
b101 *
b100 4
0(
b101011000 5
1"
#280
0"
#290
b101 4
b110 *
1(
b1010110000 5
1"
#300
0"
#310
b111 *
b110 4
0(
b101100000 5
1"
#320
0"
#330
b111 4
b1000 *
1(
b1011000000 5
1"
#340
0"
#350
b1001 *
b1000 4
0(
b110000000 5
1"
#360
0"
#370
b1001 4
b1010 *
1(
b1100000000 5
1"
#380
0"
#390
b1011 *
b1010 4
b1000000000 5
1"
#400
0"
#410
b0 4
b1100 *
0(
b0 5
1"
#420
0"
#430
b0 *
b11 .
b1 4
1"
